web3_premium/__init__.py
web3_premium/chains.py
web3_premium/contract.py
web3_premium/explorer.py
web3_premium/utils.py
web3_premium-0.0.17.dist-info/METADATA
web3_premium-0.0.17.dist-info/WHEEL
web3_premium-0.0.17.dist-info/licenses/LICENSE
web3_premium-0.0.17.dist-info/RECORD
