Metadata-Version: 2.1
Name: web3_premium
Version: 0.0.17
Summary: Data Science friendly wrapper for web3py
Project-URL: Homepage, https://github.com/Whynot63/web3-premium/
Project-URL: Bug Tracker, https://github.com/Whynot63/web3-premium/issues
Author-email: Dmitry Andreev <deal.d@me.com>
License: MIT License
License-File: LICENSE
Classifier: Programming Language :: Python :: 3
Requires-Python: >=3.8
Requires-Dist: web3>=5.30.0
